Metadata-Version: 2.1
Name: jk-php-tokenizer
Version: 0.2020.3.9
Summary: This python module is a tokenizer for configuration files written in PHP.
Home-page: https://github.com/jkpubsrc/python-module-jk-php-tokenizer
Author: Jürgen Knauth
Author-email: pubsrc@binary-overflow.de
License: Apache 2.0
Download-URL: https://github.com/jkpubsrc/python-module-jk-php-tokenizer/tarball/0.2020.3.9
Keywords: tokenizing,tokenizer,php
Platform: UNKNOWN
Classifier: Development Status :: 3 - Alpha
Classifier: License :: OSI Approved :: Apache Software License
